tableToDocument/__init__.py
tableToDocument/dropboxDoc.py
tableToDocument/excel.py
tableToDocument/googleDoc.py
tableToDocument/pdf.py
tableToDocument/tex.py
tableToDocument/toDoc.py
tableToDocument/word.py
tableToDocument/tests/__init__.py
tableToDocument/tests/formattingTests.py
tableToDocument/tests/latexTests.py
tableToDocument/tests/pandasTests.py
tableToDocument-1.0.5.data/scripts/init
tableToDocument-1.0.5.dist-info/LICENSE
tableToDocument-1.0.5.dist-info/METADATA
tableToDocument-1.0.5.dist-info/WHEEL
tableToDocument-1.0.5.dist-info/top_level.txt
tableToDocument-1.0.5.dist-info/RECORD
