Metadata-Version: 2.1
Name: tableToDocument
Version: 1.0.5
Summary: A package for writing python data, to human readable documents
Home-page: https://github.com/pgiank28/tableToDocument
Author: Pantelis Giankoulidis
Author-email: pantelis.giankoulidis@gmail.com
License: UNKNOWN
Platform: UNKNOWN
Classifier: Programming Language :: Python :: 3
Classifier: License :: OSI Approved :: MIT License
Classifier: Operating System :: OS Independent
Requires-Python: >=3.5
Requires-Dist: pandas
Requires-Dist: pyPDF2
